epadvertisements.py
epappdata.py
epdoc.py
epprodkey.py
pngdim.py
enderbyteprograms-18.0.dist-info/LICENSE
enderbyteprograms-18.0.dist-info/METADATA
enderbyteprograms-18.0.dist-info/WHEEL
enderbyteprograms-18.0.dist-info/top_level.txt
enderbyteprograms-18.0.dist-info/RECORD
