Metadata-Version: 2.1
Name: enderbyteprograms
Version: 18.0
Summary: Enderbyte Programs shared utility libraries
Author-email: Enderbyte Programs <enderbyteprograms@gmail.com>
Project-URL: Homepage, https://enderbyteprograms.weebly.com
Project-URL: Issues, https://github.com/Enderbyte-Programs/internal-libraries/issues
Classifier: Programming Language :: Python :: 3
Classifier: License :: OSI Approved :: MIT License
Classifier: Operating System :: OS Independent
Requires-Python: >=3.6
License-File: LICENSE
